matterlab_balances/__init__.py
matterlab_balances/base_balance.py
matterlab_balances/mt_balance.py
matterlab_balances/sartorius_balance.py
matterlab_balances/mt_wsdl/MT.Laboratory.Balance.XprXsr.V03.wsdl.jinja2
matterlab_balances/mt_wsdl/__init__.py
matterlab_balances-1.0.6.dist-info/licenses/LICENSE
matterlab_balances-1.0.6.dist-info/METADATA
matterlab_balances-1.0.6.dist-info/WHEEL
matterlab_balances-1.0.6.dist-info/entry_points.txt
matterlab_balances-1.0.6.dist-info/top_level.txt
matterlab_balances-1.0.6.dist-info/RECORD
